cstoolbox/__init__.py
cstoolbox/__version__.py
cstoolbox/http_api.py
cstoolbox/http_api_helper.py
cstoolbox/logger.py
cstoolbox/main.py
cstoolbox/mcp_helper.py
cstoolbox/browser/__init__.py
cstoolbox/browser/block.py
cstoolbox/browser/config.py
cstoolbox/browser/crawler.py
cstoolbox/browser/playwright_manager.py
cstoolbox/browser/pool.py
cstoolbox/config/__init__.py
cstoolbox/config/config.py
cstoolbox/core/__init__.py
cstoolbox/core/base_tool.py
cstoolbox/core/crawler_manager.py
cstoolbox/schema/content/10jqka.com.cn.json
cstoolbox/schema/content/163.com.json
cstoolbox/schema/content/baijiahao.baidu.com.json
cstoolbox/schema/content/blog.csdn.net.json
cstoolbox/schema/content/caifuhao.eastmoney.com.json
cstoolbox/schema/content/cctv.com.json
cstoolbox/schema/content/chinanews.com.cn.json
cstoolbox/schema/content/finance.eastmoney.com.json
cstoolbox/schema/content/finance.sina.com.cn.json
cstoolbox/schema/content/finance.yahoo.com.json
cstoolbox/schema/content/fund.eastmoney.com.json
cstoolbox/schema/content/guba.eastmoney.com.json
cstoolbox/schema/content/hexun.com.json
cstoolbox/schema/content/ifeng.com.json
cstoolbox/schema/content/jrj.com.cn.json
cstoolbox/schema/content/juejin.cn.json
cstoolbox/schema/content/m.jrj.com.cn.json
cstoolbox/schema/content/mp.weixin.qq.com.json
cstoolbox/schema/content/news.cn.json
cstoolbox/schema/content/news.qq.com.json
cstoolbox/schema/content/people.com.cn.json
cstoolbox/schema/content/portrait.gitee.com.json
cstoolbox/schema/content/sina.com.cn.json
cstoolbox/schema/content/stcn.com.json
cstoolbox/schema/content/stockstar.com.json
cstoolbox/schema/content/thepaper.cn.json
cstoolbox/schema/content/wikipedia.org.json
cstoolbox/schema/content/www.cnblogs.com.json
cstoolbox/schema/content/www.jiemian.com.json
cstoolbox/schema/content/www.msn.com.json
cstoolbox/schema/content/www.myzaker.com.json
cstoolbox/schema/content/www.nbd.com.cn.json
cstoolbox/schema/content/www.runoob.com.json
cstoolbox/schema/content/www.sohu.com.json
cstoolbox-1.0.5.dist-info/METADATA
cstoolbox-1.0.5.dist-info/WHEEL
cstoolbox-1.0.5.dist-info/entry_points.txt
cstoolbox-1.0.5.dist-info/licenses/LICENSE
cstoolbox-1.0.5.dist-info/RECORD
