Metadata-Version: 2.4
Name: cstoolbox
Version: 1.0.5
Summary: An extension toolkit for ChatSpeed, providing web search, web content crawling, and chart generation capabilities.
Project-URL: Homepage, https://github.com/aidyou/cstoolbox
Project-URL: Repository, https://github.com/aidyou/cstoolbox
Author-email: 心澄 <xc@aidyou.ai>
License: MIT
License-File: LICENSE
Requires-Python: >=3.10
Requires-Dist: aiohttp>=3.11.18
Requires-Dist: appdirs>=1.4.4
Requires-Dist: lxml>=5.3.2
Requires-Dist: markdownify>=1.1.0
Requires-Dist: matplotlib>=3.9.4
Requires-Dist: mcp[cli]>=1.6.0
Requires-Dist: pdfplumber>=0.11.6
Requires-Dist: playwright>=1.51.0
Requires-Dist: pydantic>=2.11.3
Provides-Extra: dev
